Metadata-Version: 2.1
Name: odoo10-addon-l10n-it-sdi-channel
Version: 10.0.1.2.0.99.dev11
Summary: Aggiunge il canale di invio/ricezione dei file XML attraverso lo SdI
Home-page: https://github.com/OCA/l10n-italy/tree/10.0/l10n_it_sdi_channel
Author: Efatto.it di Sergio Corato, Odoo Community Association (OCA)
Author-email: support@odoo-community.org
License: AGPL-3
Platform: UNKNOWN
Classifier: Programming Language :: Python
Classifier: Framework :: Odoo
Classifier: Framework :: Odoo :: 10.0
Classifier: License :: OSI Approved :: GNU Affero General Public License v3
Classifier: Development Status :: 3 - Alpha
Requires-Python: ~=2.7
Requires-Dist: odoo10-addon-l10n-it-fatturapa
Requires-Dist: odoo <10.1dev,>=10.0
